xueqiu_mcp/__init__.py
xueqiu_mcp/__main__.py
xueqiu_mcp/server.py
snowball_mcp-0.2.8.dist-info/METADATA
snowball_mcp-0.2.8.dist-info/WHEEL
snowball_mcp-0.2.8.dist-info/entry_points.txt
snowball_mcp-0.2.8.dist-info/licenses/LICENSE
snowball_mcp-0.2.8.dist-info/RECORD
