Metadata-Version: 2.4
Name: snowball-mcp
Version: 0.2.8
Summary: 基于雪球API的MCP服务，让您通过Claude或其他AI助手轻松获取股票数据
Project-URL: Homepage, https://github.com/xunzhimeng/xueqiu_mcp
Project-URL: Repository, https://github.com/xunzhimeng/xueqiu_mcp
Author: xunzhimeng
License-Expression: MIT
License-File: LICENSE
Keywords: ai,claude,mcp,model-context-protocol,stock,xueqiu
Classifier: Development Status :: 4 - Beta
Classifier: License :: OSI Approved :: MIT License
Classifier: Programming Language :: Python :: 3.11
Classifier: Programming Language :: Python :: 3.12
Requires-Python: >=3.11
Requires-Dist: fastmcp>=2.1.2
Requires-Dist: pysnowball>=0.1.3
Requires-Dist: python-dotenv>=1.0.0
